hashell_py-0.1.1.dist-info/METADATA
hashell_py-0.1.1.dist-info/WHEEL
hashell_py-0.1.1.dist-info/license_files/LICENSE
hashell/__init__.py
hashell/hashell.cpython-39-powerpc64le-linux-gnu.so
hashell_py-0.1.1.dist-info/RECORD
