Metadata-Version: 2.1
Name: hashell-py
Version: 0.1.1
Classifier: Programming Language :: Rust
Classifier: Programming Language :: Python :: Implementation :: CPython
Classifier: Programming Language :: Python :: Implementation :: PyPy
License-File: LICENSE
Summary: Python bindings for hashell
Author: Grisshink
Requires-Python: >=3.8
Project-URL: Homepage, https://github.com/Grisshink/hashell-py
